jiboia/__init__.py
jiboia/analysis_utils.py
jiboia/file_analysis_utils.py
jiboia/normalize_date_utils.py
jiboia/normalize_df_utils.py
jiboia/normalize_float_utils.py
jiboia/normalize_int_utils.py
jiboia/normalize_null_utils.py
jiboia/normalize_string_utils.py
jiboia/regex_patterns.py
jiboia-0.1.0.dist-info/licenses/LICENSE
jiboia-0.1.0.dist-info/METADATA
jiboia-0.1.0.dist-info/WHEEL
jiboia-0.1.0.dist-info/top_level.txt
jiboia-0.1.0.dist-info/RECORD
