Metadata-Version: 2.4
Name: jiboia
Version: 0.1.0
Summary: jiboia is a python package for automatically normalizing DataFrames and optimizing types efficiently.
Author-email: Lucas Muffato <lucasmuffato.eng@gmail.com>
License: MIT License
Project-URL: Homepage, https://github.com/lmuffato/jiboia
Project-URL: Bug_Tracker, https://github.com/lmuffato/jiboia/issues
Requires-Python: >=3.9
License-File: LICENSE
Requires-Dist: pandas>=2.0
Dynamic: license-file
